PacoteAbimael/__init__.py
PacoteAbimael/modulo.py
PacoteAbimael-0.0.1.dist-info/LICENSE
PacoteAbimael-0.0.1.dist-info/METADATA
PacoteAbimael-0.0.1.dist-info/WHEEL
PacoteAbimael-0.0.1.dist-info/top_level.txt
PacoteAbimael-0.0.1.dist-info/RECORD
