Metadata-Version: 2.1
Name: PacoteAbimael
Version: 0.0.1
Summary: Pacote python para exibir numero de 1 a 9
Home-page: https://github.com/AbimaelOliveira/pacoteAbimael
Author: Abimael Ferreira de Oliveira
Author-email: abimaelferreira2021@outlook.com
License: MIT License
Keywords: Pacote
Platform: UNKNOWN
License-File: LICENSE
Requires-Dist: numpy
